{
  "properties": {
    "connectionReferences": {
      "shared_commondataserviceforapps": {
        "runtimeSource": "embedded",
        "connection": {
          "connectionReferenceLogicalName": "bsr_DataverseApplicationUserWS2"
        },
        "api": {
          "name": "shared_commondataserviceforapps"
        }
      }
    },
    "definition": {
      "$schema": "https://schema.management.azure.com/providers/Microsoft.Logic/schemas/2016-06-01/workflowdefinition.json#",
      "contentVersion": "1.0.0.0",
      "parameters": {
        "$authentication": {
          "defaultValue": {},
          "type": "SecureObject"
        },
        "$connections": {
          "defaultValue": {},
          "type": "Object"
        }
      },
      "triggers": {
        "When_a_row_is_added,_modified_or_deleted": {
          "metadata": {
            "operationMetadataId": "c73bb631-c1ae-4f41-aebb-5ee3441482b8"
          },
          "type": "OpenApiConnectionWebhook",
          "inputs": {
            "parameters": {
              "subscriptionRequest/message": 4,
              "subscriptionRequest/entityname": "bsr_mdtmember",
              "subscriptionRequest/scope": 4,
              "subscriptionRequest/filteringattributes": "bsr_contact,bsr_jobrole",
              "subscriptionRequest/name": "d03ad382-ce58-ee11-be6f-6045bdd0e4cf"
            },
            "host": {
              "apiId": "/providers/Microsoft.PowerApps/apis/shared_commondataserviceforapps",
              "operationId": "SubscribeWebhookTrigger",
              "connectionName": "shared_commondataserviceforapps"
            }
          }
        }
      },
      "actions": {
        "Update_a_row": {
          "runAfter": {
            "Compose": [
              "Succeeded"
            ]
          },
          "metadata": {
            "operationMetadataId": "2cad0a6a-a87a-42e2-8082-7c2f4ba720b9"
          },
          "type": "OpenApiConnection",
          "inputs": {
            "parameters": {
              "entityName": "bsr_mdtmembers",
              "recordId": "@triggerOutputs()?['body/bsr_mdtmemberid']",
              "item/bsr_name": "@{outputs('Contact_Name')} - @{outputs('Compose')}"
            },
            "host": {
              "apiId": "/providers/Microsoft.PowerApps/apis/shared_commondataserviceforapps",
              "operationId": "UpdateRecord",
              "connectionName": "shared_commondataserviceforapps"
            }
          }
        },
        "Get_a_row_by_ID": {
          "runAfter": {},
          "metadata": {
            "operationMetadataId": "c40ab40b-a399-413d-9092-55cae0f6ef85"
          },
          "type": "OpenApiConnection",
          "inputs": {
            "parameters": {
              "entityName": "bsr_mdtmembers",
              "recordId": "@triggerOutputs()?['body/bsr_mdtmemberid']"
            },
            "host": {
              "apiId": "/providers/Microsoft.PowerApps/apis/shared_commondataserviceforapps",
              "operationId": "GetItem",
              "connectionName": "shared_commondataserviceforapps"
            }
          }
        },
        "Contact_Name": {
          "runAfter": {
            "Get_a_row_by_ID": [
              "Succeeded"
            ]
          },
          "metadata": {
            "operationMetadataId": "e5c19808-cfb8-4903-8207-ce0f0960b635"
          },
          "type": "Compose",
          "inputs": "@outputs('Get_a_row_by_ID')?['body/_bsr_contact_value@OData.Community.Display.V1.FormattedValue']"
        },
        "Compose": {
          "runAfter": {
            "Contact_Name": [
              "Succeeded"
            ]
          },
          "metadata": {
            "operationMetadataId": "5e6674c9-3a91-4069-8ae4-f93790d34b87"
          },
          "type": "Compose",
          "inputs": "@outputs('Get_a_row_by_ID')?['body/_bsr_jobrole_value@OData.Community.Display.V1.FormattedValue']"
        }
      }
    },
    "templateName": null
  },
  "schemaVersion": "1.0.0.0"
}