{
  "properties": {
    "connectionReferences": {
      "shared_commondataserviceforapps_1": {
        "runtimeSource": "embedded",
        "connection": {
          "connectionReferenceLogicalName": "bsr_DataverseApplicationUserWS3"
        },
        "api": {
          "name": "shared_commondataserviceforapps"
        }
      }
    },
    "definition": {
      "$schema": "https://schema.management.azure.com/providers/Microsoft.Logic/schemas/2016-06-01/workflowdefinition.json#",
      "contentVersion": "1.0.0.0",
      "parameters": {
        "$connections": {
          "defaultValue": {},
          "type": "Object"
        },
        "$authentication": {
          "defaultValue": {},
          "type": "SecureObject"
        }
      },
      "triggers": {
        "When_a_row_is_added,_modified_or_deleted": {
          "metadata": {
            "operationMetadataId": "bc33a95c-83de-4020-a2ec-2de8c5e2e01a"
          },
          "type": "OpenApiConnectionWebhook",
          "inputs": {
            "host": {
              "connectionName": "shared_commondataserviceforapps_1",
              "operationId": "SubscribeWebhookTrigger",
              "apiId": "/providers/Microsoft.PowerApps/apis/shared_commondataserviceforapps"
            },
            "parameters": {
              "subscriptionRequest/message": 4,
              "subscriptionRequest/entityname": "bsr_payment",
              "subscriptionRequest/scope": 4,
              "subscriptionRequest/filterexpression": "bsr_paymentreconciliationstatus eq 760810002"
            },
            "authentication": "@parameters('$authentication')"
          }
        }
      },
      "actions": {
        "Update_a_row": {
          "runAfter": {},
          "metadata": {
            "operationMetadataId": "f0669e24-7611-4cde-88b4-72f5f330a5d7"
          },
          "type": "OpenApiConnection",
          "inputs": {
            "host": {
              "connectionName": "shared_commondataserviceforapps_1",
              "operationId": "UpdateRecord",
              "apiId": "/providers/Microsoft.PowerApps/apis/shared_commondataserviceforapps"
            },
            "parameters": {
              "entityName": "bsr_buildingprofessionapplications",
              "recordId": "@triggerOutputs()?['body/_bsr_buildingprofessionapplicationid_value']",
              "item/statuscode": 760810007
            },
            "authentication": "@parameters('$authentication')"
          }
        }
      }
    },
    "templateName": ""
  },
  "schemaVersion": "1.0.0.0"
}